<?xml version="1.0" encoding="UTF-8"?>
<persistence version="2.0"
	xmlns="http://java.sun.com/xml/ns/persistence"
	xmlns:xsi="http://www.w3.org/2001/XMLSchema-instance"
	xsi:schemaLocation="http://java.sun.com/xml/ns/persistence http://java.sun.com/xml/ns/persistence/persistence_2_0.xsd">
	
	<persistence-unit name="derby2">
	
		<provider>org.eclipse.persistence.jpa.PersistenceProvider</provider>
		<!-- NOT REQUIRED IF USING JPA ANNOTATED CODE -->
		<!-- mapping-file>META-INF/identifiable-orm.xml</mapping-file-->
		<!-- mapping-file>META-INF/library-orm.xml</mapping-file-->
		<!-- Here must be noted all generated classes to persist -->
		<class>org.eclipse.emf.texo.test.mode.base.identifiable.Identifiable</class>
		<class>de.konstanz.htwg.spray.petrinet.InputArc</class>
		<class>de.konstanz.htwg.spray.petrinet.Net</class>
		<class>de.konstanz.htwg.spray.petrinet.OutputArc</class>
		<class>de.konstanz.htwg.spray.petrinet.Place</class>
		<class>de.konstanz.htwg.spray.petrinet.Token</class>
		<class>de.konstanz.htwg.spray.petrinet.Transition</class>
		<properties>
            <property name="eclipselink.target-database" value="org.eclipse.persistence.platform.database.DerbyPlatform"/>
            <property name="javax.persistence.jdbc.driver" value="org.apache.derby.jdbc.EmbeddedDriver"/>
            <property name="javax.persistence.jdbc.url" value="jdbc:derby:/tmp/sprayDB;create=true"/>
 
            <!-- EclipseLink should create the database schema automatically -->
            <property name="eclipselink.ddl-generation" value="create-tables" />
            <property name="eclipselink.ddl-generation.output-mode" value="database" />
		</properties>

	</persistence-unit>

	
	<persistence-unit name="mysql">
	
		<provider>org.eclipse.persistence.jpa.PersistenceProvider</provider>
		<!-- NOT REQUIRED IF USING JPA ANNOTATED CODE -->
        <!-- mapping-file>META-INF/identifiable-orm.xml</mapping-file-->
        <!-- mapping-file>META-INF/library-orm.xml</mapping-file-->
        <!-- Here must be noted all generated classes to persist -->
        <class>org.eclipse.emf.texo.test.mode.base.identifiable.Identifiable</class>
        <class>de.konstanz.htwg.spray.petrinet.InputArc</class>
        <class>de.konstanz.htwg.spray.petrinet.Net</class>
        <class>de.konstanz.htwg.spray.petrinet.OutputArc</class>
        <class>de.konstanz.htwg.spray.petrinet.Place</class>
        <class>de.konstanz.htwg.spray.petrinet.Token</class>
        <class>de.konstanz.htwg.spray.petrinet.Transition</class>
		<properties>
            <property name="eclipselink.target-database" value="Mysql"/>
            <property name="javax.persistence.jdbc.driver" value="com.mysql.jdbc.Driver"/>
            <property name="javax.persistence.jdbc.url" value="jdbc:mysql://localhost:3306/spray-ecore" />
            <property name="javax.persistence.jdbc.user" value="root"/>
            <property name="javax.persistence.jdbc.password" value="root"/>

            <!-- EclipseLink should create the database schema automatically -->

            <property name="eclipselink.ddl-generation" value="create-tables" />
            <property name="eclipselink.ddl-generation.output-mode" value="database" />
		</properties>

	</persistence-unit>
		
</persistence>